strands_hackerone/__init__.py
strands_hackerone/_version.py
strands_hackerone/hackerone.py
strands_hackerone-0.1.3.dist-info/licenses/LICENSE
strands_hackerone-0.1.3.dist-info/METADATA
strands_hackerone-0.1.3.dist-info/WHEEL
strands_hackerone-0.1.3.dist-info/top_level.txt
strands_hackerone-0.1.3.dist-info/RECORD
