Metadata-Version: 2.4
Name: strands-hackerone
Version: 0.1.3
Summary: HackerOne API tool for Strands Agents. Automate bug bounty research, program monitoring, and report management with AI.
Author-email: Cagatay Cali <cagataycali@gmail.com>
Project-URL: Homepage, https://github.com/cagataycali/strands-hackerone
Project-URL: Repository, https://github.com/cagataycali/strands-hackerone
Keywords: strands,agents,strands-agents,hackerone
Classifier: Development Status :: 4 - Beta
Classifier: Intended Audience :: Developers
Classifier: Programming Language :: Python :: 3
Classifier: Programming Language :: Python :: 3.10
Classifier: Programming Language :: Python :: 3.11
Classifier: Programming Language :: Python :: 3.12
Classifier: Programming Language :: Python :: 3.13
Requires-Python: >=3.10
License-File: LICENSE
Requires-Dist: strands-agents
Requires-Dist: requests>=2.28.0
Dynamic: license-file
